<meta>
	<include resource="html" />
	
	<oop>true</oop>
	<script src="vehicles_s.lua" type="server" />
	<script src="vehicleControl_c.lua" type="client" cache="false" />
	<script src="vehicleDamage_c.lua" type="client" cache="false" />
	<script src="vehiclesList_c.lua" type="client" cache="false" />
	<script src="vehiclesList_s.lua" type="server" />
	<script src="fuel_c.lua" type="client" cache="false" />
	<script src="mileage_c.lua" type="client" cache="false" />
	<file src="playerVehicles.html" />
	<file src="playerVehicles.js" />
	<file src="img/licznik.png" />
	<file src="img/needle.png" />

	<export function="spawnVehicle" type="server" />
	<export function="unspawnVehicle" type="server" />
	<export function="getVehicleByUID" type="server" />
	<export function="loadPlayerVehicles" type="server" />
	<export function="saveVehicle" type="server" />
	<export function="setVehicleOwner" type="server" />
</meta>